cocos/__init__.py
cocos/device.py
cocos/device_pool.py
cocos/utilities.py
cocos/multi_processing/__init__.py
cocos/multi_processing/device_pool.py
cocos/multi_processing/multi_core_batch_processing.py
cocos/multi_processing/single_device_batch_processing.py
cocos/multi_processing/single_gpu_batch_processing.py
cocos/multi_processing/utilities.py
cocos/numerics/__init__.py
cocos/numerics/_algorithm.py
cocos/numerics/_arith.py
cocos/numerics/_array.py
cocos/numerics/_conversion.py
cocos/numerics/_data.py
cocos/numerics/_utilities.py
cocos/numerics/data_types.py
cocos/numerics/numerical_package_bundle.py
cocos/numerics/numerical_package_selector.py
cocos/numerics/random.py
cocos/numerics/linalg/__init__.py
cocos/numerics/linalg/_linalg.py
cocos/options/__init__.py
cocos/scientific/__init__.py
cocos/scientific/kde.py
cocos/scientific/linalg.py
cocos/symbolic/__init__.py
cocos/symbolic/_lambdification.py
cocos/symbolic/translations.py
cocos/symbolic/utilities.py
cocos/tests/__init__.py
cocos/tests/test_dummy.py
cocos/tests/test_multiprocessing/__init__.py
cocos/tests/test_multiprocessing/test_generate_slices.py
cocos/tests/test_numerics/__init__.py
cocos/tests/test_numerics/test_dummy.py
cocos/tests/test_numerics/test_algorithm/__init__.py
cocos/tests/test_numerics/test_algorithm/test_any_all.py
cocos/tests/test_numerics/test_algorithm/test_argmin.py
cocos/tests/test_numerics/test_algorithm/test_count_nonzero.py
cocos/tests/test_numerics/test_algorithm/test_diff.py
cocos/tests/test_numerics/test_algorithm/test_dummy.py
cocos/tests/test_numerics/test_algorithm/test_nonzero.py
cocos/tests/test_numerics/test_algorithm/test_reciprocal.py
cocos/tests/test_numerics/test_algorithm/test_sort.py
cocos/tests/test_numerics/test_algorithm/test_sort_by_keys.py
cocos/tests/test_numerics/test_algorithm/test_sum_prod.py
cocos/tests/test_numerics/test_algorithm/test_union_intersection.py
cocos/tests/test_numerics/test_arith/__init__.py
cocos/tests/test_numerics/test_arith/test_binary.py
cocos-0.2.2.dist-info/LICENSE
cocos-0.2.2.dist-info/METADATA
cocos-0.2.2.dist-info/WHEEL
cocos-0.2.2.dist-info/top_level.txt
cocos-0.2.2.dist-info/RECORD
