Metadata-Version: 2.1
Name: cocos
Version: 0.2.2
Summary: Core Computational System
Home-page: https://github.com/michaelnowotny/cocos
Author: Michael Christoph Nowotny
Author-email: nowotnym@gmail.com
License: MIT
Platform: UNKNOWN
Classifier: License :: OSI Approved :: MIT License
Classifier: Programming Language :: Python
Classifier: Programming Language :: Python :: 3
Classifier: Programming Language :: Python :: 3.7
Classifier: Programming Language :: Python :: 3.8
Classifier: Programming Language :: Python :: Implementation :: CPython
Requires-Python: >=3.7.0
Requires-Dist: arrayfire
Requires-Dist: cached-property
Requires-Dist: contexttimer
Requires-Dist: loky
Requires-Dist: numpy
Requires-Dist: pathos
Requires-Dist: scipy
Requires-Dist: sympy
Requires-Dist: pytest
